setup.cfg
setup.py
doc_diff/Diff.py
doc_diff/__init__.py
doc_diff.egg-info/PKG-INFO
doc_diff.egg-info/SOURCES.txt
doc_diff.egg-info/dependency_links.txt
doc_diff.egg-info/top_level.txt