Metadata-Version: 1.1
Name: doc-diff
Version: 1.0.0
Summary: support lib to generate the diff of two CSV files
Home-page: https://github.com/Renien/doc-diff
Author: Renien
Author-email: renien.john@gmail.com
License: MIT
Download-URL: https://github.com/Renien/doc-diff/tarball/1.0.0
Keywords: doc-diff,DataScience,ComparingDocuments,ComparingAlgo
Platform: UNKNOWN
